odoo/addons/stock_picking_sale_order_link/README.rst
odoo/addons/stock_picking_sale_order_link/__init__.py
odoo/addons/stock_picking_sale_order_link/__manifest__.py
odoo/addons/stock_picking_sale_order_link/i18n/de.po
odoo/addons/stock_picking_sale_order_link/i18n/es.po
odoo/addons/stock_picking_sale_order_link/i18n/fr.po
odoo/addons/stock_picking_sale_order_link/i18n/it.po
odoo/addons/stock_picking_sale_order_link/i18n/pt.po
odoo/addons/stock_picking_sale_order_link/i18n/pt_BR.po
odoo/addons/stock_picking_sale_order_link/i18n/sl.po
odoo/addons/stock_picking_sale_order_link/i18n/stock_picking_sale_order_link.pot
odoo/addons/stock_picking_sale_order_link/i18n/tr.po
odoo/addons/stock_picking_sale_order_link/models/__init__.py
odoo/addons/stock_picking_sale_order_link/models/stock_picking.py
odoo/addons/stock_picking_sale_order_link/readme/CONTRIBUTORS.rst
odoo/addons/stock_picking_sale_order_link/readme/DESCRIPTION.rst
odoo/addons/stock_picking_sale_order_link/readme/USAGE.rst
odoo/addons/stock_picking_sale_order_link/static/description/icon.png
odoo/addons/stock_picking_sale_order_link/static/description/index.html
odoo/addons/stock_picking_sale_order_link/tests/__init__.py
odoo/addons/stock_picking_sale_order_link/tests/test_stock_picking_sale_order_link.py
odoo/addons/stock_picking_sale_order_link/views/stock_picking_view.xml
odoo12_addon_stock_picking_sale_order_link-12.0.1.0.1.dist-info/METADATA
odoo12_addon_stock_picking_sale_order_link-12.0.1.0.1.dist-info/WHEEL
odoo12_addon_stock_picking_sale_order_link-12.0.1.0.1.dist-info/top_level.txt
odoo12_addon_stock_picking_sale_order_link-12.0.1.0.1.dist-info/RECORD
